scrawler_itau/__init__.py
scrawler_itau/scrawler_itau.py
scrawler_itau-0.2.3.dist-info/LICENSE
scrawler_itau-0.2.3.dist-info/METADATA
scrawler_itau-0.2.3.dist-info/WHEEL
scrawler_itau-0.2.3.dist-info/top_level.txt
scrawler_itau-0.2.3.dist-info/RECORD
