Metadata-Version: 2.1
Name: scrawler_itau
Version: 0.2.3
Summary: Extrator de dados bancários do Itaú utilizando Selenium
Home-page: https://github.com/mbiemann/scrawler-banco-itau
Author: Marcell Biemann
Author-email: mbiemann@gmail.com
Project-URL: Bug Tracker, https://github.com/mbiemann/scrawler-banco-itau/issues
Classifier: Programming Language :: Python :: 3
Classifier: License :: OSI Approved :: MIT License
Classifier: Operating System :: OS Independent
Requires-Python: >=3.6
License-File: LICENSE
Requires-Dist: selenium ==3.141.0
